example/__init__.py
example/settings.py
example/urls.py
example/wsgi.py
smsish/__init__.py
smsish/admin.py
smsish/models.py
smsish/tasks.py
smsish/tests.py
smsish/views.py
smsish/mail/__init__.py
smsish/mail/utils.py
smsish/mail/backends/__init__.py
smsish/mail/backends/mailtrap.py
smsish/migrations/__init__.py
smsish/sms/__init__.py
smsish/sms/message.py
smsish/sms/backends/__init__.py
smsish/sms/backends/base.py
smsish/sms/backends/console.py
smsish/sms/backends/dummy.py
smsish/sms/backends/filebased.py
smsish/sms/backends/locmem.py
smsish/sms/backends/mailcatcher.py
smsish/sms/backends/mailtrap.py
smsish/sms/backends/rq.py
smsish/sms/backends/smtp.py
smsish/sms/backends/twilio.py
smsish/sms/backends/yunpian.py
django_smsish2-1.3.5.dist-info/LICENSE
django_smsish2-1.3.5.dist-info/METADATA
django_smsish2-1.3.5.dist-info/WHEEL
django_smsish2-1.3.5.dist-info/top_level.txt
django_smsish2-1.3.5.dist-info/RECORD
